README.md
setup.cfg
setup.py
citcall/__init__.py
citcall/citcall.py
citcall_py.egg-info/PKG-INFO
citcall_py.egg-info/SOURCES.txt
citcall_py.egg-info/dependency_links.txt
citcall_py.egg-info/top_level.txt