Metadata-Version: 2.1
Name: citcall-py
Version: 0.1.1
Summary: Citcall REST API for Python
Home-page: https://github.com/saggafarsyad/citcall-python
Author: Saggaf Arsyad
Author-email: saggaf@nbs.co.id
License: MIT
Platform: UNKNOWN
Classifier: Programming Language :: Python :: 3
Classifier: License :: OSI Approved :: MIT License
Classifier: Operating System :: OS Independent
Requires-Python: >=3.5
